{"filename":"/data/__azurite_db_blob__.json","collections":[{"name":"$SERVICES_COLLECTION$","data":[],"idIndex":null,"binaryIndices":{},"constraints":null,"uniqueNames":["accountName"],"transforms":{},"objType":"$SERVICES_COLLECTION$","dirty":false,"cachedIndex":null,"cachedBinaryIndex":null,"cachedData":null,"adaptiveBinaryIndices":true,"transactional":false,"cloneObjects":false,"cloneMethod":"parse-stringify","asyncListeners":false,"disableMeta":false,"disableChangesApi":true,"disableDeltaChangesApi":true,"autoupdate":false,"serializableIndices":true,"disableFreeze":true,"ttl":null,"maxId":0,"DynamicViews":[],"events":{"insert":[],"update":[],"pre-insert":[],"pre-update":[],"close":[],"flushbuffer":[],"error":[],"delete":[null],"warning":[null]},"changes":[],"dirtyIds":[]},{"name":"$CONTAINERS_COLLECTION$","data":[{"accountName":"devstoreaccount1","name":"ecommerce-dev-blob","properties":{"etag":"\"0x1E663A3D3C72B90\"","lastModified":"2024-05-06T11:42:07.897Z","leaseStatus":"unlocked","leaseState":"available","hasImmutabilityPolicy":false,"hasLegalHold":false},"meta":{"revision":0,"created":1714995727935,"version":0},"$loki":1}],"idIndex":null,"binaryIndices":{"accountName":{"name":"accountName","dirty":false,"values":[0]},"name":{"name":"name","dirty":false,"values":[0]}},"constraints":null,"uniqueNames":[],"transforms":{},"objType":"$CONTAINERS_COLLECTION$","dirty":false,"cachedIndex":null,"cachedBinaryIndex":null,"cachedData":null,"adaptiveBinaryIndices":true,"transactional":false,"cloneObjects":false,"cloneMethod":"parse-stringify","asyncListeners":false,"disableMeta":false,"disableChangesApi":true,"disableDeltaChangesApi":true,"autoupdate":false,"serializableIndices":true,"disableFreeze":true,"ttl":null,"maxId":1,"DynamicViews":[],"events":{"insert":[],"update":[],"pre-insert":[],"pre-update":[],"close":[],"flushbuffer":[],"error":[],"delete":[null],"warning":[null]},"changes":[],"dirtyIds":[]},{"name":"$BLOBS_COLLECTION$","data":[{"deleted":false,"accountName":"devstoreaccount1","containerName":"ecommerce-dev-blob","name":"Users/ee03f6c5-74c3-4a2b-9409-3b62bf9f180b.png","properties":{"creationTime":"2024-05-06T11:42:07.963Z","lastModified":"2024-05-06T11:42:07.963Z","etag":"\"0x246B7C119516F80\"","contentLength":259342,"contentType":"image/png","contentMD5":{"type":"Buffer","data":[49,170,86,25,221,216,38,103,73,175,234,14,231,196,181,153]},"blobType":"BlockBlob","leaseStatus":"unlocked","leaseState":"available","serverEncrypted":true,"accessTier":"Hot","accessTierInferred":true,"accessTierChangeTime":"2024-05-06T11:42:07.963Z"},"snapshot":"","isCommitted":true,"persistency":{"id":"c35ad53e-16b8-4dca-961b-123605878c69","offset":0,"count":259342},"meta":{"revision":0,"created":1714995727974,"version":0},"$loki":1},{"deleted":false,"accountName":"devstoreaccount1","containerName":"ecommerce-dev-blob","name":"Products/9c26e1c9-28b8-4cee-b09a-0954b5693202.jpeg","properties":{"creationTime":"2024-05-09T17:50:30.146Z","lastModified":"2024-05-09T17:50:30.146Z","etag":"\"0x1E0FF26E0CEEA50\"","contentLength":11973,"contentType":"image/jpeg","contentMD5":{"type":"Buffer","data":[134,71,130,146,224,175,226,183,216,54,21,232,33,207,30,31]},"blobType":"BlockBlob","leaseStatus":"unlocked","leaseState":"available","serverEncrypted":true,"accessTier":"Hot","accessTierInferred":true,"accessTierChangeTime":"2024-05-09T17:50:30.146Z"},"snapshot":"","isCommitted":true,"persistency":{"id":"1f944448-72d7-444a-ab1f-06723be08bd9","offset":309165,"count":11973},"meta":{"revision":0,"created":1715277030150,"version":0},"$loki":51},{"deleted":false,"accountName":"devstoreaccount1","containerName":"ecommerce-dev-blob","name":"Products/c4a3f9b6-3d0a-43ef-b1e2-b66f98ed8bf1.jpeg","properties":{"creationTime":"2024-05-09T17:57:28.059Z","lastModified":"2024-05-09T17:57:28.059Z","etag":"\"0x1E9E664E3CD6DE0\"","contentLength":7618,"contentType":"image/jpeg","contentMD5":{"type":"Buffer","data":[14,201,228,4,186,34,68,68,19,169,60,210,200,60,194,159]},"blobType":"BlockBlob","leaseStatus":"unlocked","leaseState":"available","serverEncrypted":true,"accessTier":"Hot","accessTierInferred":true,"accessTierChangeTime":"2024-05-09T17:57:28.059Z"},"snapshot":"","isCommitted":true,"persistency":{"id":"1f944448-72d7-444a-ab1f-06723be08bd9","offset":321138,"count":7618},"meta":{"revision":0,"created":1715277448063,"version":0},"$loki":52},{"deleted":false,"accountName":"devstoreaccount1","containerName":"ecommerce-dev-blob","name":"Products/b8b80d03-4aec-48de-bd87-bd92e6449fd8.jpeg","properties":{"creationTime":"2024-05-09T17:59:45.114Z","lastModified":"2024-05-09T17:59:45.114Z","etag":"\"0x1CAF7A979EBF680\"","contentLength":9485,"contentType":"image/jpeg","contentMD5":{"type":"Buffer","data":[71,65,169,187,199,40,82,164,14,133,101,177,249,218,175,138]},"blobType":"BlockBlob","leaseStatus":"unlocked","leaseState":"available","serverEncrypted":true,"accessTier":"Hot","accessTierInferred":true,"accessTierChangeTime":"2024-05-09T17:59:45.114Z"},"snapshot":"","isCommitted":true,"persistency":{"id":"1f944448-72d7-444a-ab1f-06723be08bd9","offset":328756,"count":9485},"meta":{"revision":0,"created":1715277585117,"version":0},"$loki":53},{"deleted":false,"accountName":"devstoreaccount1","containerName":"ecommerce-dev-blob","name":"Products/f8b64082-67fe-4b30-a0a9-26c087e05bb1.jpeg","properties":{"creationTime":"2024-05-09T18:05:29.775Z","lastModified":"2024-05-09T18:05:29.775Z","etag":"\"0x1FDC106F853CBE0\"","contentLength":10892,"contentType":"image/jpeg","contentMD5":{"type":"Buffer","data":[93,209,77,185,146,118,250,81,201,16,200,4,232,215,184,139]},"blobType":"BlockBlob","leaseStatus":"unlocked","leaseState":"available","serverEncrypted":true,"accessTier":"Hot","accessTierInferred":true,"accessTierChangeTime":"2024-05-09T18:05:29.775Z"},"snapshot":"","isCommitted":true,"persistency":{"id":"1f944448-72d7-444a-ab1f-06723be08bd9","offset":338241,"count":10892},"meta":{"revision":0,"created":1715277929780,"version":0},"$loki":54},{"deleted":false,"accountName":"devstoreaccount1","containerName":"ecommerce-dev-blob","name":"Products/8e9e33af-14a5-4508-aa96-db536bc55cd3.jpeg","properties":{"creationTime":"2024-05-09T18:09:03.051Z","lastModified":"2024-05-09T18:09:03.051Z","etag":"\"0x1B3E2484C643A40\"","contentLength":5192,"contentType":"image/jpeg","contentMD5":{"type":"Buffer","data":[120,95,219,241,37,59,7,188,28,36,148,96,98,176,120,5]},"blobType":"BlockBlob","leaseStatus":"unlocked","leaseState":"available","serverEncrypted":true,"accessTier":"Hot","accessTierInferred":true,"accessTierChangeTime":"2024-05-09T18:09:03.051Z"},"snapshot":"","isCommitted":true,"persistency":{"id":"1f944448-72d7-444a-ab1f-06723be08bd9","offset":349133,"count":5192},"meta":{"revision":0,"created":1715278143055,"version":0},"$loki":55},{"deleted":false,"accountName":"devstoreaccount1","containerName":"ecommerce-dev-blob","name":"Products/d3fe19ae-fc69-4837-986c-c2ee4181fe84.jpeg","properties":{"creationTime":"2024-05-09T18:11:55.266Z","lastModified":"2024-05-09T18:11:55.266Z","etag":"\"0x208CA4860DD6260\"","contentLength":12541,"contentType":"image/jpeg","contentMD5":{"type":"Buffer","data":[151,138,110,176,243,184,85,42,194,69,58,29,130,7,115,155]},"blobType":"BlockBlob","leaseStatus":"unlocked","leaseState":"available","serverEncrypted":true,"accessTier":"Hot","accessTierInferred":true,"accessTierChangeTime":"2024-05-09T18:11:55.266Z"},"snapshot":"","isCommitted":true,"persistency":{"id":"1f944448-72d7-444a-ab1f-06723be08bd9","offset":354325,"count":12541},"meta":{"revision":0,"created":1715278315270,"version":0},"$loki":56},{"deleted":false,"accountName":"devstoreaccount1","containerName":"ecommerce-dev-blob","name":"Products/51b55313-59f3-46dd-a1e4-9263858675ee.jpeg","properties":{"creationTime":"2024-05-09T18:15:08.727Z","lastModified":"2024-05-09T18:15:08.727Z","etag":"\"0x1B27860B00D2C00\"","contentLength":10684,"contentType":"image/jpeg","contentMD5":{"type":"Buffer","data":[153,192,149,18,1,132,237,20,111,38,149,26,98,97,243,81]},"blobType":"BlockBlob","leaseStatus":"unlocked","leaseState":"available","serverEncrypted":true,"accessTier":"Hot","accessTierInferred":true,"accessTierChangeTime":"2024-05-09T18:15:08.727Z"},"snapshot":"","isCommitted":true,"persistency":{"id":"1f944448-72d7-444a-ab1f-06723be08bd9","offset":366866,"count":10684},"meta":{"revision":0,"created":1715278508730,"version":0},"$loki":57},{"deleted":false,"accountName":"devstoreaccount1","containerName":"ecommerce-dev-blob","name":"Products/035f61aa-10b5-4193-a8fa-e507d4073015.jpeg","properties":{"creationTime":"2024-05-09T18:16:39.639Z","lastModified":"2024-05-09T18:16:39.639Z","etag":"\"0x1FFE6360D6C26B0\"","contentLength":8548,"contentType":"image/jpeg","contentMD5":{"type":"Buffer","data":[224,95,187,205,162,144,171,198,159,229,17,251,104,248,2,8]},"blobType":"BlockBlob","leaseStatus":"unlocked","leaseState":"available","serverEncrypted":true,"accessTier":"Hot","accessTierInferred":true,"accessTierChangeTime":"2024-05-09T18:16:39.639Z"},"snapshot":"","isCommitted":true,"persistency":{"id":"1f944448-72d7-444a-ab1f-06723be08bd9","offset":377550,"count":8548},"meta":{"revision":0,"created":1715278599642,"version":0},"$loki":58},{"deleted":false,"accountName":"devstoreaccount1","containerName":"ecommerce-dev-blob","name":"Products/50908657-b913-4cb0-ac4a-20b49b3d1a0c.jpeg","properties":{"creationTime":"2024-05-09T18:23:47.184Z","lastModified":"2024-05-09T18:23:47.184Z","etag":"\"0x22DDD9AB4128800\"","contentLength":7661,"contentType":"image/jpeg","contentMD5":{"type":"Buffer","data":[80,239,225,57,96,141,199,39,203,169,238,141,144,177,172,108]},"blobType":"BlockBlob","leaseStatus":"unlocked","leaseState":"available","serverEncrypted":true,"accessTier":"Hot","accessTierInferred":true,"accessTierChangeTime":"2024-05-09T18:23:47.184Z"},"snapshot":"","isCommitted":true,"persistency":{"id":"1f944448-72d7-444a-ab1f-06723be08bd9","offset":386098,"count":7661},"meta":{"revision":0,"created":1715279027188,"version":0},"$loki":59},{"deleted":false,"accountName":"devstoreaccount1","containerName":"ecommerce-dev-blob","name":"Products/eae7ad66-9911-4a1d-bed9-f939cb7a5ae8.jpeg","properties":{"creationTime":"2024-05-09T18:26:10.825Z","lastModified":"2024-05-09T18:26:10.825Z","etag":"\"0x1D35BF1287944D0\"","contentLength":20533,"contentType":"image/jpeg","contentMD5":{"type":"Buffer","data":[200,177,219,111,193,247,54,61,71,243,164,61,244,77,221,3]},"blobType":"BlockBlob","leaseStatus":"unlocked","leaseState":"available","serverEncrypted":true,"accessTier":"Hot","accessTierInferred":true,"accessTierChangeTime":"2024-05-09T18:26:10.825Z"},"snapshot":"","isCommitted":true,"persistency":{"id":"1f944448-72d7-444a-ab1f-06723be08bd9","offset":393759,"count":20533},"meta":{"revision":0,"created":1715279170829,"version":0},"$loki":60},{"deleted":false,"accountName":"devstoreaccount1","containerName":"ecommerce-dev-blob","name":"Products/6500ff77-8171-4250-a878-a29bcfd5ddb2.jpeg","properties":{"creationTime":"2024-05-09T18:46:36.981Z","lastModified":"2024-05-09T18:46:36.981Z","etag":"\"0x2204B8344CDB460\"","contentLength":13154,"contentType":"image/jpeg","contentMD5":{"type":"Buffer","data":[60,19,230,29,190,5,190,236,67,244,13,245,168,41,91,55]},"blobType":"BlockBlob","leaseStatus":"unlocked","leaseState":"available","serverEncrypted":true,"accessTier":"Hot","accessTierInferred":true,"accessTierChangeTime":"2024-05-09T18:46:36.981Z"},"snapshot":"","isCommitted":true,"persistency":{"id":"1f944448-72d7-444a-ab1f-06723be08bd9","offset":414292,"count":13154},"meta":{"revision":0,"created":1715280396985,"version":0},"$loki":61},{"deleted":false,"accountName":"devstoreaccount1","containerName":"ecommerce-dev-blob","name":"Users/b5417342-17ec-4f92-ae48-fd8fc8487ffd.jpg","properties":{"creationTime":"2024-05-11T07:39:36.270Z","lastModified":"2024-05-11T07:39:36.270Z","etag":"\"0x20A7D20D6EE4500\"","contentLength":201923,"contentType":"image/jpeg","contentMD5":{"type":"Buffer","data":[177,194,53,142,131,22,135,214,51,250,241,62,114,138,238,226]},"blobType":"BlockBlob","leaseStatus":"unlocked","leaseState":"available","serverEncrypted":true,"accessTier":"Hot","accessTierInferred":true,"accessTierChangeTime":"2024-05-11T07:39:36.270Z"},"snapshot":"","isCommitted":true,"persistency":{"id":"0a0c8df5-f679-427e-ba3b-7203ca130968","offset":0,"count":201923},"meta":{"revision":0,"created":1715413176282,"version":0},"$loki":62}],"idIndex":null,"binaryIndices":{"accountName":{"name":"accountName","dirty":false,"values":[12,11,10,9,8,7,6,5,4,3,2,1,0]},"containerName":{"name":"containerName","dirty":false,"values":[12,11,10,9,8,7,6,5,4,3,2,1,0]},"name":{"name":"name","dirty":false,"values":[8,9,7,11,5,1,3,2,6,10,4,12,0]},"snapshot":{"name":"snapshot","dirty":false,"values":[12,11,10,9,8,7,6,5,4,3,2,1,0]}},"constraints":null,"uniqueNames":[],"transforms":{},"objType":"$BLOBS_COLLECTION$","dirty":false,"cachedIndex":null,"cachedBinaryIndex":null,"cachedData":null,"adaptiveBinaryIndices":true,"transactional":false,"cloneObjects":false,"cloneMethod":"parse-stringify","asyncListeners":false,"disableMeta":false,"disableChangesApi":true,"disableDeltaChangesApi":true,"autoupdate":false,"serializableIndices":true,"disableFreeze":true,"ttl":null,"maxId":62,"DynamicViews":[],"events":{"insert":[],"update":[],"pre-insert":[],"pre-update":[],"close":[],"flushbuffer":[],"error":[],"delete":[null],"warning":[null]},"changes":[],"dirtyIds":[]},{"name":"$BLOCKS_COLLECTION$","data":[],"idIndex":null,"binaryIndices":{"accountName":{"name":"accountName","dirty":false,"values":[]},"containerName":{"name":"containerName","dirty":false,"values":[]},"blobName":{"name":"blobName","dirty":false,"values":[]},"name":{"name":"name","dirty":false,"values":[]}},"constraints":null,"uniqueNames":[],"transforms":{},"objType":"$BLOCKS_COLLECTION$","dirty":false,"cachedIndex":null,"cachedBinaryIndex":null,"cachedData":null,"adaptiveBinaryIndices":true,"transactional":false,"cloneObjects":false,"cloneMethod":"parse-stringify","asyncListeners":false,"disableMeta":false,"disableChangesApi":true,"disableDeltaChangesApi":true,"autoupdate":false,"serializableIndices":true,"disableFreeze":true,"ttl":null,"maxId":0,"DynamicViews":[],"events":{"insert":[],"update":[],"pre-insert":[],"pre-update":[],"close":[],"flushbuffer":[],"error":[],"delete":[null],"warning":[null]},"changes":[],"dirtyIds":[]}],"databaseVersion":1.5,"engineVersion":1.5,"autosave":true,"autosaveInterval":5000,"autosaveHandle":null,"throttledSaves":true,"options":{"persistenceMethod":"fs","autosave":true,"autosaveInterval":5000,"serializationMethod":"normal","destructureDelimiter":"$<\n"},"persistenceMethod":"fs","persistenceAdapter":null,"verbose":false,"events":{"init":[null],"loaded":[],"flushChanges":[],"close":[],"changes":[],"warning":[]},"ENV":"NODEJS"}